burki/__init__.py
burki/auth.py
burki/client.py
burki/exceptions.py
burki/http_client.py
burki/py.typed
burki/models/__init__.py
burki/models/assistant.py
burki/models/call.py
burki/models/campaign.py
burki/models/document.py
burki/models/phone_number.py
burki/models/realtime.py
burki/models/sms.py
burki/models/tool.py
burki/realtime/__init__.py
burki/realtime/campaign_progress.py
burki/realtime/client.py
burki/realtime/live_transcript.py
burki/resources/__init__.py
burki/resources/assistants.py
burki/resources/base.py
burki/resources/calls.py
burki/resources/campaigns.py
burki/resources/documents.py
burki/resources/phone_numbers.py
burki/resources/sms.py
burki/resources/tools.py
burki-0.1.2.dist-info/METADATA
burki-0.1.2.dist-info/WHEEL
burki-0.1.2.dist-info/RECORD
