Metadata-Version: 2.4
Name: burki
Version: 0.1.2
Summary: Official Python SDK for the Burki Voice AI Platform
Project-URL: Homepage, https://burki.dev
Project-URL: Documentation, https://docs.burki.dev
Project-URL: Repository, https://github.com/SymbioticSystems/burki-sdks
Project-URL: Changelog, https://github.com/SymbioticSystems/burki-sdks/blob/main/python/CHANGELOG.md
Author-email: Burki <support@burki.dev>
License-Expression: MIT
Keywords: api,assistants,burki,sdk,telephony,voice-ai
Classifier: Development Status :: 4 - Beta
Classifier: Intended Audience :: Developers
Classifier: License :: OSI Approved :: MIT License
Classifier: Operating System :: OS Independent
Classifier: Programming Language :: Python :: 3
Classifier: Programming Language :: Python :: 3.8
Classifier: Programming Language :: Python :: 3.9
Classifier: Programming Language :: Python :: 3.10
Classifier: Programming Language :: Python :: 3.11
Classifier: Programming Language :: Python :: 3.12
Classifier: Topic :: Software Development :: Libraries :: Python Modules
Classifier: Typing :: Typed
Requires-Python: >=3.8
Requires-Dist: httpx>=0.25.0
Requires-Dist: pydantic>=2.0.0
Requires-Dist: websockets>=12.0
Provides-Extra: dev
Requires-Dist: mypy>=1.0.0; extra == 'dev'
Requires-Dist: pytest-asyncio>=0.21.0; extra == 'dev'
Requires-Dist: pytest>=7.0.0; extra == 'dev'
Requires-Dist: ruff>=0.1.0; extra == 'dev'
